doccli/__init__.py
doccli/config.py
doccli/parse.py
sid_doc_cli-0.0.5.dist-info/LICENSE
sid_doc_cli-0.0.5.dist-info/METADATA
sid_doc_cli-0.0.5.dist-info/WHEEL
sid_doc_cli-0.0.5.dist-info/RECORD
