Metadata-Version: 2.1
Name: sid-doc-cli
Version: 0.0.5
Summary: Build Config classes that can be quickly turned into CLI specifications
Home-page: https://github.com/siddu2020/doccli/
License: Apache-2.0
Author: siddu2020
Author-email: siddartha.k2020@gmail.com
Requires-Python: >=3.10,<4.0
Classifier: License :: OSI Approved :: Apache Software License
Classifier: Programming Language :: Python :: 3
Classifier: Programming Language :: Python :: 3.10
Classifier: Programming Language :: Python :: 3.11
Requires-Dist: decli (>=0.5.1,<0.6.0)
Requires-Dist: docstring-parser (>=0.3,<0.4)
Requires-Dist: pyyaml (>=5.1.2,<6.0.0)
Project-URL: Repository, https://github.com/siddu2020/doccli
